s_and_p_500_grabber/__init__.py
s_and_p_500_grabber/s_and_p_grabber.py
s_and_p_500_grabber-0.3.dist-info/LICENSE
s_and_p_500_grabber-0.3.dist-info/METADATA
s_and_p_500_grabber-0.3.dist-info/WHEEL
s_and_p_500_grabber-0.3.dist-info/top_level.txt
s_and_p_500_grabber-0.3.dist-info/RECORD
