Metadata-Version: 2.1
Name: s-and-p-500-grabber
Version: 0.3
Summary: A free S&P 500 list getter.
Home-page: https://gitlab.com/zeastman/s_and_p_500_grabber
Author: Zachariah Eastman
Author-email: zachariah.d.eastman@gmail.com
License: MIT
Platform: UNKNOWN
Requires-Dist: requests
Requires-Dist: bs4
